omicsone/__init__.py
omicsone/command_line.py
omicsone/gui_tkinter.py
omicsone/main.py
omicsone/server.py
omicsone/assets/bWLwgP.css
omicsone/assets/brPBPO.css
omicsone/database/glycositeatlas_human_2016.xlsx
omicsone/database/glycosylation_enzymes_20210826.xlsx
omicsone/database/protein.txt
omicsone/plugins/__init__.py
omicsone/plugins/callbacks.cp38-win_amd64.pyd
omicsone/plugins/defaults.cp38-win_amd64.pyd
omicsone/plugins/diff.cp38-win_amd64.pyd
omicsone/plugins/future.cp38-win_amd64.pyd
omicsone/plugins/layout.cp38-win_amd64.pyd
omicsone/plugins/pca1.cp38-win_amd64.pyd
omicsone/plugins/preprocess.cp38-win_amd64.pyd
omicsone/plugins/survival.cp38-win_amd64.pyd
omicsone/plugins/toolkit.cp38-win_amd64.pyd
omicsone/plugins/utils.cp38-win_amd64.pyd
omicsone/plugins/visual_dash.cp38-win_amd64.pyd
omicsone/plugins/webapp.cp38-win_amd64.pyd
omicsone/plugins/assets/bWLwgP.css
omicsone/samples/CPTAC_LSCC_meta_info.xlsx
omicsone/samples/CPTAC_LSCC_proteome.xlsx
omicsone/samples/CPTAC_OVA_glycoform_log2r_20210811.txt
omicsone/samples/CPTAC_OVA_meta_info.txt
omicsone/samples/CPTAC_OVA_protein_log2r_20210811.txt
omicsone-1.1.8.dist-info/LICENSE
omicsone-1.1.8.dist-info/METADATA
omicsone-1.1.8.dist-info/WHEEL
omicsone-1.1.8.dist-info/entry_points.txt
omicsone-1.1.8.dist-info/top_level.txt
omicsone-1.1.8.dist-info/RECORD
