Metadata-Version: 2.1
Name: omicsone
Version: 1.1.8
Summary: OmicsOne: phenotype association analysis
Home-page: 
Author: Yingwei Hu, Minghui Ao
Author-email: yhu39@jhmi.edu
License: Apache 2.0
Platform: UNKNOWN
License-File: LICENSE
Requires-Dist: ansi2html (==1.7.0)
Requires-Dist: appdirs (==1.4.4)
Requires-Dist: asttokens (==2.0.5)
Requires-Dist: attrs (==21.4.0)
Requires-Dist: backcall (==0.2.0)
Requires-Dist: beautifulsoup4 (==4.11.1)
Requires-Dist: bioservices (==1.8.4)
Requires-Dist: Brotli (==1.0.9)
Requires-Dist: cattrs (==1.10.0)
Requires-Dist: certifi (==2021.10.8)
Requires-Dist: cffi (==1.15.0)
Requires-Dist: charset-normalizer (==2.0.12)
Requires-Dist: click (==8.1.2)
Requires-Dist: colorama (==0.4.4)
Requires-Dist: colorlog (==6.6.0)
Requires-Dist: cycler (==0.11.0)
Requires-Dist: dash (==2.0.0)
Requires-Dist: dash-core-components (==2.0.0)
Requires-Dist: dash-html-components (==2.0.0)
Requires-Dist: dash-table (==5.0.0)
Requires-Dist: debugpy (==1.6.0)
Requires-Dist: decorator (==5.1.1)
Requires-Dist: easydev (==0.12.0)
Requires-Dist: entrypoints (==0.4)
Requires-Dist: et-xmlfile (==1.1.0)
Requires-Dist: executing (==0.8.3)
Requires-Dist: Flask (==2.1.1)
Requires-Dist: Flask-Compress (==1.11)
Requires-Dist: fonttools (==4.32.0)
Requires-Dist: gevent (==21.12.0)
Requires-Dist: greenlet (==1.1.2)
Requires-Dist: grequests (==0.6.0)
Requires-Dist: gseapy (==0.10.5)
Requires-Dist: idna (==3.3)
Requires-Dist: importlib-metadata (==4.11.3)
Requires-Dist: ipykernel (==6.13.0)
Requires-Dist: ipython (==8.2.0)
Requires-Dist: itsdangerous (==2.1.2)
Requires-Dist: jedi (==0.18.1)
Requires-Dist: Jinja2 (==3.1.1)
Requires-Dist: joblib (==1.1.0)
Requires-Dist: jupyter-client (==7.2.2)
Requires-Dist: jupyter-core (==4.9.2)
Requires-Dist: jupyter-dash (==0.4.0)
Requires-Dist: kiwisolver (==1.4.2)
Requires-Dist: lxml (==4.8.0)
Requires-Dist: MarkupSafe (==2.1.1)
Requires-Dist: matplotlib (==3.5.1)
Requires-Dist: matplotlib-inline (==0.1.3)
Requires-Dist: nest-asyncio (==1.5.5)
Requires-Dist: numpy (==1.21.4)
Requires-Dist: openpyxl (==3.0.9)
Requires-Dist: packaging (==21.3)
Requires-Dist: pandas (==1.4.2)
Requires-Dist: parso (==0.8.3)
Requires-Dist: patsy (==0.5.2)
Requires-Dist: pexpect (==4.8.0)
Requires-Dist: pickleshare (==0.7.5)
Requires-Dist: Pillow (==9.1.0)
Requires-Dist: plotly (==5.7.0)
Requires-Dist: prompt-toolkit (==3.0.29)
Requires-Dist: psutil (==5.9.0)
Requires-Dist: ptyprocess (==0.7.0)
Requires-Dist: pure-eval (==0.2.2)
Requires-Dist: pycparser (==2.21)
Requires-Dist: Pygments (==2.11.2)
Requires-Dist: pyparsing (==3.0.8)
Requires-Dist: python-dateutil (==2.8.2)
Requires-Dist: pytz (==2022.1)
Requires-Dist: pywin32 (==303)
Requires-Dist: pyzmq (==22.3.0)
Requires-Dist: requests (==2.27.1)
Requires-Dist: requests-cache (==0.9.3)
Requires-Dist: retrying (==1.3.3)
Requires-Dist: scikit-learn (==0.24.2)
Requires-Dist: scikit-plot (==0.3.7)
Requires-Dist: scipy (==1.7.1)
Requires-Dist: seaborn (==0.11.2)
Requires-Dist: six (==1.16.0)
Requires-Dist: soupsieve (==2.3.2.post1)
Requires-Dist: stack-data (==0.2.0)
Requires-Dist: statsmodels (==0.13.2)
Requires-Dist: suds-community (==1.1.0)
Requires-Dist: tenacity (==8.0.1)
Requires-Dist: threadpoolctl (==3.1.0)
Requires-Dist: tornado (==6.1)
Requires-Dist: tqdm (==4.64.0)
Requires-Dist: traitlets (==5.1.1)
Requires-Dist: url-normalize (==1.4.3)
Requires-Dist: urllib3 (==1.26.9)
Requires-Dist: wcwidth (==0.2.5)
Requires-Dist: Werkzeug (==2.0.3)
Requires-Dist: wincertstore (==0.2)
Requires-Dist: wrapt (==1.14.0)
Requires-Dist: xmltodict (==0.12.0)
Requires-Dist: zipp (==3.8.0)
Requires-Dist: zope.event (==4.5.0)
Requires-Dist: zope.interface (==5.4.0)
